<?xml version="1.0"?>
<directory><file name="." timestamp="1348621493"/><file name="home" timestamp="1331601010" icon_position="64,102"/><file name="trash" timestamp="1331601010" icon_position="64,282"/><file name="computer" timestamp="1331601010" icon_position="64,22"/><file name="%2Fexport%2Foud08%2F1%20(405.2%20GB).volume" timestamp="1331601010" icon_position="64,182"/><file name="%2Fexport%2Fpipe18%2F1%20(237.5%20GB).volume" timestamp="1331618727" icon_position="64,382"/><file name="%2Fexport%2Fpipe10%2F1%20(237.5%20GB).volume" timestamp="1332828596" icon_position="64,382"/><file name="%2Fexport%2Fpipe11%2F1%20(237.5%20GB).volume" timestamp="1332828722" icon_position="64,382"/><file name="%2Fexport%2Fleaf03%2F1%20(237.5%20GB).volume" timestamp="1339975762" icon_position="64,482"/><file name="%2Fexport%2Fsanhu16%2F1%20(237.5%20GB).volume" timestamp="1339990666" icon_position="64,382"/><file name="%2Fexport%2Fsanhu11%2F1%20(237.5%20GB).volume" timestamp="1339990997" icon_position="64,382"/><file name="%2Fexport%2Fsanhu23%2F1%20(237.5%20GB).volume" timestamp="1340004010" icon_position="64,382"/><file name="%2Fexport%2Fsanhu13%2F1%20(237.5%20GB).volume" timestamp="1340245009" icon_position="64,382"/><file name="%2Fexport%2Fbanjo15%2F1%20(405.2%20GB).volume" timestamp="1342757371" icon_position="64,382"/><file name="%2Fexport%2Fbanjo07%2F1%20(405.2%20GB).volume" timestamp="1342761292" icon_position="64,382"/><file name="%2Fexport%2Fleaf10%2F1%20(237.5%20GB).volume" timestamp="1343174781" icon_position="64,382"/><file name="%2Fexport%2Fsanhu06%2F1%20(237.5%20GB).volume" timestamp="1343363861" icon_position="64,382"/><file name="%2Fexport%2Fleaf01%2F1%20(237.5%20GB).volume" timestamp="1343779490" icon_position="64,382"/><file name="%2Fexport%2Fbugle15%2F1%20(237.5%20GB).volume" timestamp="1343797500" icon_position="64,382"/><file name="%2Fexport%2Fleaf15%2F1%20(237.5%20GB).volume" timestamp="1343891156" icon_position="64,382"/><file name="%2Fexport%2Fspoons07%2F1%20(237.5%20GB).volume" timestamp="1343973217" icon_position="64,382"/><file name="%2Fexport%2Fspoons15%2F1%20(237.5%20GB).volume" timestamp="1344301451" icon_position="64,382"/><file name="%2Fexport%2Fpipe19%2F1%20(237.5%20GB).volume" timestamp="1344407207" icon_position="64,382"/><file name="%2Fexport%2Fpipe00%2F1%20(237.5%20GB).volume" timestamp="1344492870" icon_position="64,382"/><file name="%2Fexport%2Fspoons01%2F1%20(237.5%20GB).volume" timestamp="1344830089" icon_position="64,382"/><file name="%2Fexport%2Fleaf00%2F1%20(237.5%20GB).volume" timestamp="1344989363" icon_position="64,382"/><file name="%2Fexport%2Fbell05%2F1%20(237.5%20GB).volume" timestamp="1345174417" icon_position="64,382"/><file name="%2Fexport%2Fleaf05%2F1%20(237.5%20GB).volume" timestamp="1345183316" icon_position="64,382"/><file name="%2Fexport%2Fbell06%2F1%20(237.5%20GB).volume" timestamp="1345522158" icon_position="64,382"/><file name="%2Fexport%2Fmoog10%2F1%20(237.5%20GB).volume" timestamp="1345782453" icon_position="64,382"/><file name="%2Fexport%2Fpipe13%2F1%20(237.5%20GB).volume" timestamp="1346045642" icon_position="64,382"/><file name="%2Fexport%2Fleaf14%2F1%20(237.5%20GB).volume" timestamp="1346311554" icon_position="64,382"/><file name="%2Fexport%2Fspoons17%2F1%20(237.5%20GB).volume" timestamp="1348463269" icon_position="64,382"/><file name="%2Fexport%2Fleaf02%2F1%20(237.5%20GB).volume" timestamp="1348617989" icon_position="64,382"/></directory>
